processpi/__init__.py
processpi/constants.py
processpi/calculations/__init__.py
processpi/calculations/base.py
processpi/calculations/engine.py
processpi/calculations/fluids/__init__.py
processpi/calculations/fluids/flow_type.py
processpi/calculations/fluids/friction_factor_colebrookwhite.py
processpi/calculations/fluids/optimium_pipe_dia.py
processpi/calculations/fluids/pressure_drop_darcy.py
processpi/calculations/fluids/pressure_drop_fanning.py
processpi/calculations/fluids/pressure_drop_hazen_williams.py
processpi/calculations/fluids/pump_power.py
processpi/calculations/fluids/reynolds_number.py
processpi/calculations/fluids/velocity.py
processpi/calculations/heat_transfer/__init__.py
processpi/calculations/heat_transfer/biot.py
processpi/calculations/heat_transfer/boiling_chen.py
processpi/calculations/heat_transfer/combined_modes.py
processpi/calculations/heat_transfer/condensation.py
processpi/calculations/heat_transfer/condensation_dropwise.py
processpi/calculations/heat_transfer/condensation_nusselt.py
processpi/calculations/heat_transfer/conduction_heat_loss.py
processpi/calculations/heat_transfer/convection_heat_loss.py
processpi/calculations/heat_transfer/crossflow_tube.py
processpi/calculations/heat_transfer/fourier.py
processpi/calculations/heat_transfer/fourierlaw.py
processpi/calculations/heat_transfer/grashof.py
processpi/calculations/heat_transfer/heat_exchanger_area.py
processpi/calculations/heat_transfer/lmtd.py
processpi/calculations/heat_transfer/newton_cooling.py
processpi/calculations/heat_transfer/ntu.py
processpi/calculations/heat_transfer/nusselt.py
processpi/calculations/heat_transfer/overall_u.py
processpi/calculations/heat_transfer/peclet.py
processpi/calculations/heat_transfer/prandtl.py
processpi/calculations/heat_transfer/radial_cylinder.py
processpi/calculations/heat_transfer/radiation_blackbody.py
processpi/calculations/heat_transfer/radiation_exchange.py
processpi/calculations/heat_transfer/radiation_greybody.py
processpi-0.2.0.dist-info/licenses/LICENSE
processpi-0.2.0.dist-info/METADATA
processpi-0.2.0.dist-info/WHEEL
processpi-0.2.0.dist-info/top_level.txt
processpi-0.2.0.dist-info/RECORD
