Metadata-Version: 2.4
Name: processpi
Version: 0.2.0
Summary: Python toolkit for chemical engineering simulations, equipment design, and unit conversions
Home-page: https://github.com/varma666/ProcessPi
Author: Raviteja Varma Nadimpalli
Author-email: Raviteja Varma Nadimpalli <processpi.dev@gmail.com>
License: MIT License
Project-URL: Homepage, https://github.com/varma666/ProcessPi
Project-URL: BugTracker, https://github.com/varma666/ProcessPi/issues
Project-URL: SourceCode, https://github.com/varma666/ProcessPi
Requires-Python: >=3.8
License-File: LICENSE
Requires-Dist: tabulate>=0.9.0
Requires-Dist: matplotlib>=3.7.0
Requires-Dist: networkx>=3.1
Requires-Dist: CoolProp>=6.5.0
Requires-Dist: tqdm>=4.65.0
Requires-Dist: plotly>=5.18.0
Dynamic: author
Dynamic: home-page
Dynamic: license-file
Dynamic: requires-python
